<?xml version="1.0" encoding="UTF-8" ?>
<odoo>
    <data>

        <record id="view_account_form_vat_report" model="ir.ui.view">
            <field name="name">account.account.form.vat.report</field>
            <field name="model">account.account</field>
            <field name="inherit_id" ref="account.view_account_form"/>
            <field name="arch" type="xml">
                <field name="internal_group" position="after">
                    <field name="is_a_vat_account"/>
                </field>
            </field>
        </record>

    </data>
</odoo>